{
  "meta": {
    "run_date": "2026-04-23",
    "portfolio_value_usd": 1296.17,
    "cost_basis_usd": 653.7,
    "unrealized_pnl_usd": 642.46,
    "unrealized_pnl_pct": 98.28,
    "n_simulations": 25000,
    "simulation_days": 504,
    "history_years": 10,
    "gbp_usd": 1.3487,
    "eur_usd": 1.1705,
    "excluded_tickers": []
  },
  "assets": [
    {
      "ticker": "M7U.DE",
      "qty": 10.0,
      "price_local": 21.3,
      "price_usd": 24.9327,
      "value_usd": 249.33,
      "weight_pct": 19.24,
      "vol_annual_pct": 26.51,
      "mu_annual_pct": -4.92,
      "nu": 2.53,
      "available_years": 10.1,
      "bootstrapped_years": 0.0,
      "cost_price_local": 11.39,
      "cost_basis_usd": 133.33
    },
    {
      "ticker": "AAOI",
      "qty": 1.2,
      "price_local": 149.42,
      "price_usd": 149.42,
      "value_usd": 179.3,
      "weight_pct": 13.83,
      "vol_annual_pct": 54.92,
      "mu_annual_pct": -4.07,
      "nu": 2.73,
      "available_years": 10.0,
      "bootstrapped_years": 0.0,
      "cost_price_local": 102.02,
      "cost_basis_usd": 122.42
    },
    {
      "ticker": "AXTI",
      "qty": 3.0,
      "price_local": 86.94,
      "price_usd": 86.94,
      "value_usd": 260.82,
      "weight_pct": 20.12,
      "vol_annual_pct": 48.16,
      "mu_annual_pct": 3.53,
      "nu": 2.95,
      "available_years": 10.0,
      "bootstrapped_years": 0.0,
      "cost_price_local": 48.0,
      "cost_basis_usd": 144.0
    },
    {
      "ticker": "SOI.PA",
      "qty": 2.1,
      "price_local": 106.0,
      "price_usd": 124.0782,
      "value_usd": 260.56,
      "weight_pct": 20.1,
      "vol_annual_pct": 31.73,
      "mu_annual_pct": 27.01,
      "nu": 3.25,
      "available_years": 10.2,
      "bootstrapped_years": 0.0,
      "cost_price_local": 54.38,
      "cost_basis_usd": 133.67
    },
    {
      "ticker": "IQE.L",
      "qty": 270.0,
      "price_local": 56.9,
      "price_usd": 0.7674,
      "value_usd": 207.19,
      "weight_pct": 15.99,
      "vol_annual_pct": 40.29,
      "mu_annual_pct": -13.33,
      "nu": 2.75,
      "available_years": 10.0,
      "bootstrapped_years": 0.0,
      "cost_price_local": 0.2521,
      "cost_basis_usd": 0.92
    },
    {
      "ticker": "LITE",
      "qty": 0.09,
      "price_local": 873.6,
      "price_usd": 873.6,
      "value_usd": 78.62,
      "weight_pct": 6.07,
      "vol_annual_pct": 35.38,
      "mu_annual_pct": 51.23,
      "nu": 3.17,
      "available_years": 10.0,
      "bootstrapped_years": 0.0,
      "cost_price_local": 674.9,
      "cost_basis_usd": 60.74
    },
    {
      "ticker": "LNSR",
      "qty": 6.0,
      "price_local": 5.44,
      "price_usd": 5.44,
      "value_usd": 32.64,
      "weight_pct": 2.52,
      "vol_annual_pct": 36.52,
      "mu_annual_pct": -39.9,
      "nu": 2.41,
      "available_years": 5.5,
      "bootstrapped_years": 4.5,
      "cost_price_local": 6.08,
      "cost_basis_usd": 36.48
    },
    {
      "ticker": "IVV",
      "qty": 0.02,
      "price_local": 714.56,
      "price_usd": 714.56,
      "value_usd": 14.29,
      "weight_pct": 1.1,
      "vol_annual_pct": 9.75,
      "mu_annual_pct": 26.66,
      "nu": 2.52,
      "available_years": 10.0,
      "bootstrapped_years": 0.0,
      "cost_price_local": 609.56,
      "cost_basis_usd": 12.19
    },
    {
      "ticker": "P4O.DE",
      "qty": 1.0,
      "price_local": 11.45,
      "price_usd": 13.4028,
      "value_usd": 13.4,
      "weight_pct": 1.03,
      "vol_annual_pct": 0.0,
      "mu_annual_pct": -0.0,
      "nu": 2.1,
      "available_years": 10.1,
      "bootstrapped_years": 0.0,
      "cost_price_local": 8.5,
      "cost_basis_usd": 9.95
    }
  ],
  "simulation": {
    "percentile_paths": {
      "p5": [
        1296.1676538111763,
        1293.7160935001996,
        1292.4166051243956,
        1291.1869336027596,
        1290.265722448403,
        1289.2717262273898,
        1288.4556419644318,
        1287.5931876016803,
        1287.0193008250253,
        1286.2857873172272,
        1285.589847746675,
        1284.9290332244316,
        1284.3309538439973,
        1283.7200914915163,
        1283.1381108774326,
        1282.5710726045168,
        1281.9119079550658,
        1281.409180906351,
        1280.755104198886,
        1280.1473158368121,
        1279.7188143346318,
        1279.0682808778145,
        1278.5881559723914,
        1278.1067847264999,
        1277.6451186192942,
        1277.1894046300508,
        1276.7071599135961,
        1276.2504195433485,
        1275.814899490566,
        1275.3168944553988,
        1274.8457559566189,
        1274.403576168701,
        1274.0087011409873,
        1273.4550339399111,
        1273.1050764609815,
        1272.647433193425,
        1272.2253483839766,
        1271.8491967173077,
        1271.4788003614242,
        1270.9835011191,
        1270.7467704754552,
        1270.3690247970542,
        1269.9766717417272,
        1269.5101210913845,
        1269.18625301741,
        1268.850359432729,
        1268.591217349526,
        1268.2482984293458,
        1267.9347860821638,
        1267.5581561853603,
        1267.0859184396063,
        1266.6392192507003,
        1266.5002583520452,
        1266.0902218382494,
        1265.7694871252293,
        1265.346359170343,
        1265.0741558549792,
        1264.78688608441,
        1264.4323109721176,
        1264.091393926408,
        1263.864718183812,
        1263.522894197789,
        1263.1756208598563,
        1262.854519501753,
        1262.552061841524,
        1262.14679523447,
        1261.8960686635758,
        1261.6476296410272,
        1261.2750506971913,
        1260.9004111830207,
        1260.5932424453954,
        1260.356944921279,
        1259.966848902882,
        1259.5274387434717,
        1259.2883728152608,
        1259.1666949962234,
        1258.757761219297,
        1258.4933636634885,
        1258.1382127876968,
        1257.8063517989817,
        1257.603082129412,
        1257.3765696558996,
        1257.1333007305864,
        1256.9053107697516,
        1256.705147461212,
        1256.4737662028456,
        1256.0355082874369,
        1255.8436377591895,
        1255.6185265496347,
        1255.3315434645215,
        1255.187336011582,
        1254.8938059056397,
        1254.6792332507187,
        1254.2008479288136,
        1254.1886260821639,
        1253.8809271584862,
        1253.6775520284805,
        1253.4709061483736,
        1253.2256776940642,
        1252.926912081933,
        1252.8044635543524,
        1252.8805532908136,
        1252.438535626866,
        1252.0727318317865,
        1252.0028293240548,
        1251.6596247626185,
        1251.2776915637924,
        1250.995240873479,
        1250.7160176693062,
        1250.5130231834826,
        1250.4712367738089,
        1250.053369137992,
        1250.036542810807,
        1249.8234508542123,
        1249.8503902248374,
        1249.4914018387212,
        1249.3205365556894,
        1248.8751382598596,
        1248.69571516998,
        1248.350031126108,
        1248.0881547785498,
        1247.9985345988268,
        1247.747498165421,
        1247.5944386848148,
        1247.2923624156087,
        1247.2605402981321,
        1247.0094174442952,
        1246.8209950739238,
        1246.6357234215873,
        1246.427373395229,
        1246.3116838515716,
        1246.0502064287348,
        1245.9015971431413,
        1245.677710319079,
        1245.6437433305643,
        1245.3516424957163,
        1245.2232960253427,
        1244.919692780093,
        1244.8304688405647,
        1244.7143895490287,
        1244.667059735548,
        1244.379217207131,
        1244.2828860310535,
        1244.0636947083335,
        1243.8510323507035,
        1243.655956725528,
        1243.559853368242,
        1243.4235502258489,
        1243.1676473486639,
        1243.0658488927545,
        1243.0003422272498,
        1243.0151370984229,
        1242.7865014857641,
        1242.7303125082792,
        1242.3699602422591,
        1242.075289943571,
        1242.0133370592357,
        1241.8399974475765,
        1241.7040382851915,
        1241.8251759181614,
        1241.5231773718856,
        1241.2420603013222,
        1241.0283663715088,
        1240.9875354114279,
        1240.7435757563353,
        1240.7349830489707,
        1240.6767525103792,
        1240.5237682740485,
        1240.3118198186817,
        1240.1805765802158,
        1239.9893387094496,
        1239.9558360018484,
        1239.6702915642795,
        1239.5334645611663,
        1239.4875729135808,
        1239.3574464523974,
        1239.3520843764245,
        1238.805198010913,
        1238.7864456133218,
        1238.6231015869014,
        1238.5190239776116,
        1238.4581884135023,
        1238.2996661737498,
        1238.2145266834643,
        1238.1842486612159,
        1238.0107159117383,
        1237.8203930205555,
        1237.6135029181494,
        1237.5977563530946,
        1237.4171125408561,
        1237.1102964005158,
        1236.9465676077943,
        1237.133019290906,
        1237.0148914976778,
        1236.7569153653542,
        1236.6350031389698,
        1236.5573450281067,
        1236.6270921750518,
        1236.630433478571,
        1236.5380627901814,
        1236.438882460006,
        1236.4396001224993,
        1236.3188198632874,
        1236.226670206188,
        1236.2829295128136,
        1236.2505524423468,
        1236.04773889941,
        1235.9842124380682,
        1235.8840147980156,
        1235.6529075338817,
        1235.7593263821655,
        1235.703133114746,
        1235.4458799038268,
        1235.2937650952176,
        1235.5164657291587,
        1235.3060036377726,
        1235.361684760936,
        1235.4850223594376,
        1235.5233538775844,
        1235.369368193045,
        1235.2895887049046,
        1235.3085042778425,
        1235.3294056515851,
        1235.2853632739632,
        1235.0083312450508,
        1234.9338723189305,
        1234.5927732326159,
        1234.606252942152,
        1234.6746626986267,
        1234.8280131971985,
        1234.694351832179,
        1234.7579504836706,
        1234.8743166213355,
        1234.6232644226952,
        1234.7771577632036,
        1234.5184836577946,
        1234.3735444368476,
        1234.3796721615272,
        1234.2840478516587,
        1234.2799071165114,
        1234.340398345504,
        1234.306734303809,
        1234.0952422171283,
        1233.9508355143776,
        1234.1000860426827,
        1233.9379880525016,
        1234.0122504282797,
        1234.073879430796,
        1234.0655117330489,
        1233.99581415933,
        1234.0035852100566,
        1234.0670770473337,
        1233.9481574897125,
        1233.9889306185062,
        1233.9473710112252,
        1233.7401024504709,
        1233.866118142853,
        1233.8658595573816,
        1233.8349077383205,
        1233.9540405515138,
        1233.9208344884064,
        1233.940389468659,
        1233.7242796157989,
        1233.6642437241755,
        1233.7171614220445,
        1233.5473733380634,
        1233.6282732737102,
        1233.7013690336714,
        1233.6682240308544,
        1233.6564766750062,
        1233.7211951591592,
        1233.7199342394163,
        1233.6789095659642,
        1233.750619551126,
        1233.7641871595115,
        1233.70755452864,
        1234.0056807458157,
        1233.9319212685389,
        1234.082480854156,
        1233.994546075485,
        1233.9077182870537,
        1233.9179891583767,
        1233.787368145296,
        1233.9034949202405,
        1234.2093459355128,
        1234.23515064199,
        1234.161256234151,
        1234.1606500377336,
        1234.2215466428668,
        1234.1415419962607,
        1234.1163023717068,
        1234.1896735204243,
        1234.2613393386212,
        1234.1355152839149,
        1234.4265825755735,
        1234.318915399959,
        1234.4192660170747,
        1234.461429438735,
        1234.3689121239422,
        1234.276626072166,
        1234.4101522496971,
        1234.3568823218934,
        1234.5157686676273,
        1234.55216052674,
        1234.8608208218916,
        1234.8570791652924,
        1234.7905702208975,
        1234.9370884258362,
        1234.9196522614025,
        1235.036012592477,
        1235.0574426646845,
        1234.9272980217643,
        1235.037865577801,
        1235.2172654736648,
        1235.1435750214832,
        1235.2208885468162,
        1235.3727947583238,
        1235.541633806331,
        1235.531510768493,
        1235.6632280199503,
        1235.717713426256,
        1235.9805784918121,
        1235.7750229270032,
        1235.9677910109954,
        1236.0609625122377,
        1235.9263859299515,
        1236.2501698436995,
        1236.213650675848,
        1236.4046894975168,
        1236.3578960061764,
        1236.4673894621997,
        1236.5324571963802,
        1236.6278869264193,
        1236.5796882808127,
        1236.5997267124806,
        1236.5220589927292,
        1236.7926903326386,
        1236.8505190789042,
        1237.1479607499648,
        1237.364452952717,
        1237.414784188397,
        1237.2300015497901,
        1237.4035477907976,
        1237.3307642429413,
        1237.3112558615044,
        1237.3927286552132,
        1237.641656440842,
        1237.9663819121847,
        1238.1877107270068,
        1238.1474561823702,
        1238.0952348220326,
        1237.9689389345526,
        1238.0682005282115,
        1238.2346990483784,
        1238.288068185955,
        1238.3958265940091,
        1238.561306409223,
        1238.5834966105426,
        1238.9100379652523,
        1239.1992570034065,
        1239.0288023264811,
        1239.2726418992406,
        1239.3893415817588,
        1239.50615228119,
        1239.5054206398443,
        1239.6143053911019,
        1239.610118559211,
        1239.7087265938146,
        1240.0507789839278,
        1240.0628586605844,
        1240.2684787829485,
        1240.4108984214681,
        1240.2865882959848,
        1240.7289454952097,
        1240.7521178666316,
        1240.9512609577098,
        1241.2862948333548,
        1241.4693062026547,
        1241.6088777610048,
        1241.747791494039,
        1241.66189172389,
        1241.7446018539304,
        1242.1872978345814,
        1242.068823188675,
        1242.3107528966984,
        1242.4374228075264,
        1242.5259056229656,
        1242.5598013018425,
        1242.911027847946,
        1242.984411072229,
        1243.1531097040724,
        1243.273394287736,
        1243.472607116579,
        1243.5992850000218,
        1243.7205124255127,
        1243.8164422216119,
        1243.875310516177,
        1244.2017307843068,
        1244.34452579743,
        1244.571320023833,
        1244.8134503042463,
        1244.9604586657742,
        1245.0891209900353,
        1244.9835155376902,
        1245.407876946852,
        1245.5016054369864,
        1245.6672653398332,
        1245.770798722372,
        1245.8296099239412,
        1246.1492189901896,
        1246.464439836306,
        1246.3411763947677,
        1246.5033749071713,
        1246.7815306582154,
        1246.7323616397086,
        1247.0619172340448,
        1247.0684984920074,
        1247.349113426276,
        1247.6765080535695,
        1247.5961628757445,
        1247.6029826383733,
        1247.7609497942137,
        1248.1637720129747,
        1248.4031026735474,
        1248.4993862437714,
        1248.5777988877599,
        1248.7481393373143,
        1249.1275703987217,
        1249.3824184627213,
        1249.197108910145,
        1249.4319797461453,
        1249.720459814281,
        1249.8388878864823,
        1249.99137988534,
        1250.157648910257,
        1250.1182021294023,
        1250.1988286604858,
        1250.7574336322405,
        1251.0125088433524,
        1251.0708427320772,
        1251.27934913765,
        1251.450760413523,
        1251.5313787158925,
        1251.7108623827414,
        1252.033610289427,
        1252.1608974605094,
        1252.449989595432,
        1252.8521074940302,
        1252.9781280471877,
        1253.09836182683,
        1253.3091375001413,
        1253.7274295834898,
        1253.588907924975,
        1253.8460580651176,
        1253.8407148160593,
        1254.2479377782724,
        1254.3665748792034,
        1254.8590823208888,
        1255.10543672473,
        1255.4597509405867,
        1255.457651104728,
        1255.957380206317,
        1255.826105508452,
        1256.0453444058326,
        1256.3608356163202,
        1256.417066939041,
        1256.6971228662362,
        1257.1258204080602,
        1257.5102122719363,
        1257.6556099232785,
        1257.8526319537502,
        1258.141577826356,
        1258.419230680849,
        1258.6839715169267,
        1258.8897557163423,
        1259.2252392104576,
        1259.268080014307,
        1259.6466817494413,
        1259.9579737339193,
        1260.4066132242947,
        1260.446525916027,
        1260.639462850018,
        1260.98343218353,
        1261.3689323373453,
        1261.7120732222581,
        1261.978045862013,
        1262.0324655435438,
        1262.3157840012368,
        1262.6351898909913,
        1262.775560575382,
        1263.0590872029911,
        1263.0736801268156,
        1263.3308235017132,
        1263.8350768205107,
        1264.1594422328558,
        1264.432777045171,
        1264.62418554646,
        1264.92700981895,
        1265.386466632789,
        1265.4788579755152,
        1265.7143554480706,
        1266.2141722700155,
        1266.3250223532305,
        1266.5155755174972,
        1266.67078679636
      ],
      "p25": [
        1296.1676538111763,
        1295.363004344827,
        1294.791263970052,
        1294.258976137593,
        1293.7983990568296,
        1293.38332221137,
        1292.9879073979905,
        1292.5866252942587,
        1292.2431013568855,
        1291.8893833203856,
        1291.5070734119554,
        1291.144846655112,
        1290.8079939675956,
        1290.528425306296,
        1290.2358151249168,
        1289.9215042531914,
        1289.5870862750976,
        1289.2786913364334,
        1288.9545142108145,
        1288.6778592550231,
        1288.3481597712362,
        1288.074155451044,
        1287.8529990811066,
        1287.582453275294,
        1287.294755649081,
        1287.0500518130766,
        1286.8139892294982,
        1286.5395115666622,
        1286.2145669398128,
        1285.9903155218444,
        1285.7315445145623,
        1285.4701168633123,
        1285.2452476264366,
        1285.040578507261,
        1284.795197808491,
        1284.5783651583265,
        1284.324962696524,
        1284.1029639993428,
        1283.8726085373926,
        1283.6074341106298,
        1283.4063290654396,
        1283.1565371588676,
        1282.9899435698103,
        1282.7619600941337,
        1282.5041020979086,
        1282.2923559123353,
        1282.074856191771,
        1281.8366619384958,
        1281.6295076026931,
        1281.4496787002154,
        1281.2214581056726,
        1280.999450847429,
        1280.7799269468974,
        1280.5123785824003,
        1280.35308711949,
        1280.134912431574,
        1279.9161921057332,
        1279.658521827216,
        1279.4728186610448,
        1279.3036148283086,
        1279.2215139760729,
        1279.077475333674,
        1278.8233781053575,
        1278.6194290451278,
        1278.4551666459965,
        1278.2687639521075,
        1278.0866231230002,
        1277.934673272774,
        1277.828509555141,
        1277.6334628630373,
        1277.5290384484533,
        1277.3299312428326,
        1277.176937353358,
        1276.932625040972,
        1276.7342793136606,
        1276.6095860947576,
        1276.4680924210109,
        1276.3327459571858,
        1276.1897436195177,
        1276.0994258461867,
        1275.8691864342156,
        1275.7090195690482,
        1275.5838939414966,
        1275.4431602032937,
        1275.2487229117255,
        1275.0949429153459,
        1274.9381472330617,
        1274.7528329626768,
        1274.6601382095703,
        1274.5385720714858,
        1274.349885156106,
        1274.3168142756967,
        1274.1865231306656,
        1274.0315229464566,
        1273.8898786461907,
        1273.7942656886908,
        1273.6598835065026,
        1273.4797935133802,
        1273.380657944629,
        1273.2227548725023,
        1273.1327806159657,
        1273.0376753701037,
        1272.8939708673788,
        1272.7551528441927,
        1272.6419563041245,
        1272.4819275402351,
        1272.4407650965325,
        1272.256878888107,
        1272.1221618912168,
        1271.9450501379686,
        1271.8912104352828,
        1271.6482857495123,
        1271.5325303883553,
        1271.3186108143352,
        1271.2920940368128,
        1271.242201083178,
        1271.1179823877355,
        1270.8940717955843,
        1270.7382518162487,
        1270.62869778416,
        1270.4308811027126,
        1270.4244419854008,
        1270.299267036102,
        1270.150311313208,
        1270.1412573887767,
        1270.061134978054,
        1269.9520984774363,
        1269.9078228369765,
        1269.7668694838887,
        1269.657446269868,
        1269.5226801749614,
        1269.4221517735841,
        1269.3439439499325,
        1269.2088522817003,
        1269.0925291209956,
        1269.01429400272,
        1268.9826406720551,
        1268.9089056600371,
        1268.8085861655277,
        1268.7394422678324,
        1268.6633395277279,
        1268.5069969895503,
        1268.3545441192985,
        1268.3726640768466,
        1268.366367710205,
        1268.2756543639834,
        1268.2398077038179,
        1268.0684855156674,
        1267.964057576733,
        1267.8500732326074,
        1267.7570610762166,
        1267.7402574308396,
        1267.6465922132857,
        1267.5364888414333,
        1267.483240008445,
        1267.4057299572664,
        1267.2943630467616,
        1267.2763542121766,
        1267.0780385941107,
        1267.0172354575204,
        1266.9763838081738,
        1266.930055072195,
        1266.8920380147988,
        1266.7972657104544,
        1266.7394721506028,
        1266.6374991867403,
        1266.6807345754282,
        1266.6355236064253,
        1266.554452687609,
        1266.547856842893,
        1266.5098685081657,
        1266.4600771089501,
        1266.4404178749937,
        1266.3527783394998,
        1266.3136930104129,
        1266.319426187345,
        1266.252711746723,
        1266.3110909639918,
        1266.2065103036623,
        1265.9598458258388,
        1265.9956013368794,
        1266.0224013393238,
        1265.9729685502082,
        1266.04006382368,
        1265.9843565823976,
        1265.9024460386217,
        1265.8124263157229,
        1265.8257510326757,
        1265.739365962706,
        1265.6966758413769,
        1265.6623831096329,
        1265.6610258143533,
        1265.6796055779562,
        1265.7008436263102,
        1265.708729834111,
        1265.5907313879502,
        1265.5448913099683,
        1265.4687502054708,
        1265.4848086414222,
        1265.4680655801917,
        1265.368174028194,
        1265.2975720473569,
        1265.2917450563875,
        1265.2854158325026,
        1265.2866868071303,
        1265.28092739425,
        1265.2994891099295,
        1265.2766861230084,
        1265.2682877509126,
        1265.2991775279293,
        1265.3118137287324,
        1265.2806490814578,
        1265.2739585519082,
        1265.2964130247858,
        1265.1586104054202,
        1265.252188337111,
        1265.21623528031,
        1265.2772450502675,
        1265.2191060479015,
        1265.2040971159547,
        1265.205984969897,
        1265.189813646556,
        1265.200860026305,
        1265.2527636807513,
        1265.2170538715702,
        1265.289119814546,
        1265.2640845228402,
        1265.176862968335,
        1265.160604739085,
        1265.143377761765,
        1265.1961284093827,
        1265.1691269896005,
        1265.1856095560263,
        1265.186455612467,
        1265.2985905607857,
        1265.2728791569116,
        1265.2962191550705,
        1265.3261484685179,
        1265.3367577905733,
        1265.34684360723,
        1265.315428286178,
        1265.3081413011337,
        1265.3274900824454,
        1265.4028059704788,
        1265.590301882439,
        1265.6404023160208,
        1265.6880626802592,
        1265.7978395700652,
        1265.6994221163704,
        1265.7450398007445,
        1265.8208176034736,
        1265.9072132040665,
        1265.8723183141528,
        1265.8952805722386,
        1265.8430596427493,
        1265.8418247516076,
        1266.0453346171457,
        1266.1063127780549,
        1266.1725089562428,
        1266.1323318434606,
        1266.1426704931328,
        1266.0675245963764,
        1266.1727038576478,
        1266.1546243414796,
        1266.2519740018506,
        1266.4291789735594,
        1266.4812594888451,
        1266.4876811554827,
        1266.658775901377,
        1266.725804475756,
        1266.8204642411574,
        1266.849857542252,
        1266.8496369475267,
        1266.8600878441287,
        1266.84179761934,
        1267.1501409829716,
        1267.122175737867,
        1267.2197767793623,
        1267.3089529324682,
        1267.4198421263877,
        1267.4018816124146,
        1267.5038958422965,
        1267.514858281568,
        1267.593679726696,
        1267.6674925886218,
        1267.7321710769097,
        1267.7327080242626,
        1267.8129208166831,
        1267.8835668330985,
        1268.0083947577782,
        1268.1618226415783,
        1268.2202241434609,
        1268.3492502731706,
        1268.4380598756372,
        1268.578774601684,
        1268.646822808474,
        1268.7722390295737,
        1268.7611151906003,
        1268.8876527184902,
        1268.8920918130798,
        1268.8682160468802,
        1269.0029520360004,
        1269.1091944434054,
        1269.2550189245237,
        1269.3716643115029,
        1269.5554295797606,
        1269.6348732155634,
        1269.6925060782958,
        1269.8892260916914,
        1269.9979691767849,
        1269.9948085596516,
        1270.174252999877,
        1270.2806656552325,
        1270.3607126137586,
        1270.494242238238,
        1270.554566336485,
        1270.7016592133236,
        1270.8110918764228,
        1270.8867275280463,
        1271.0425270545647,
        1271.129767392939,
        1271.2132775664118,
        1271.391234890293,
        1271.4850015604902,
        1271.5680669735184,
        1271.6144472886044,
        1271.758247553847,
        1271.705137782908,
        1271.8884600389742,
        1271.9404116639573,
        1272.156119813463,
        1272.2582909425814,
        1272.378206103831,
        1272.4085395395007,
        1272.513527171283,
        1272.5993722779413,
        1272.7407371195263,
        1272.7936244025364,
        1272.9460465942086,
        1273.1599578566816,
        1273.3307389153817,
        1273.547963903903,
        1273.6342895222829,
        1273.7937012442012,
        1273.9113897076243,
        1274.0033093450425,
        1274.233671424274,
        1274.3043661452252,
        1274.449150447955,
        1274.6670344327677,
        1274.7355656237594,
        1274.9354123610547,
        1275.0613687420505,
        1275.1218654216818,
        1275.2884081808056,
        1275.5118283937447,
        1275.6319946841177,
        1275.7518395720288,
        1275.9139189344044,
        1276.1348985539673,
        1276.209208446516,
        1276.343006303484,
        1276.4098046101485,
        1276.6007992853754,
        1276.745133672118,
        1276.9471529049179,
        1277.0361258541693,
        1277.2412566564776,
        1277.3345017250865,
        1277.410822630679,
        1277.5345507110114,
        1277.698527889538,
        1277.9322176235298,
        1278.302357609226,
        1278.514423354779,
        1278.5008734350697,
        1278.7275787762612,
        1278.9067748171044,
        1279.0438571493266,
        1279.081729277171,
        1279.2815353774574,
        1279.40098689577,
        1279.587967855845,
        1279.7666398068063,
        1280.0318617928692,
        1280.1483897952976,
        1280.3367317112516,
        1280.4551125240037,
        1280.5926069360862,
        1280.7480501721063,
        1280.9198478783812,
        1281.2085432177885,
        1281.4525195125143,
        1281.5511777390816,
        1281.7994037197955,
        1281.9783621942604,
        1282.189968939632,
        1282.3168363873704,
        1282.5779214346246,
        1282.8417113941462,
        1283.1540639138384,
        1283.3801491837705,
        1283.5524684714696,
        1283.8425770475242,
        1283.965997007088,
        1284.1219656311189,
        1284.224426369755,
        1284.399790816436,
        1284.5987840240875,
        1284.8244092913187,
        1285.1091006024749,
        1285.2684308808714,
        1285.6424184988962,
        1285.7610814129478,
        1285.9696492121302,
        1286.1478623290736,
        1286.4131652510775,
        1286.677916875617,
        1286.8977295781926,
        1287.1834203423052,
        1287.3786193438405,
        1287.6443833119654,
        1287.797599228473,
        1288.0672864840715,
        1288.291734245245,
        1288.4944554532465,
        1288.6261836951376,
        1288.7940390061553,
        1289.0373067036508,
        1289.2551131433443,
        1289.4211118447743,
        1289.6239410302255,
        1289.9065112738149,
        1290.0989851461798,
        1290.3825300296494,
        1290.6990976080958,
        1290.9569680925767,
        1291.1664603002953,
        1291.4719593077475,
        1291.6725148981504,
        1291.8095985843217,
        1292.0937240064839,
        1292.317031016114,
        1292.6539365904052,
        1292.8011646374287,
        1293.1282604913144,
        1293.3864589674104,
        1293.7030253541961,
        1294.167789064957,
        1294.2648475569174,
        1294.4716523401057,
        1294.8956592826837,
        1295.1349684136403,
        1295.4130296281628,
        1295.6194368680758,
        1295.7851253232154,
        1296.082906758686,
        1296.3104521511736,
        1296.589415086197,
        1296.9049548153214,
        1297.253683606302,
        1297.5517792241467,
        1297.7338850474823,
        1297.988951826073,
        1298.3652294782603,
        1298.5389886650528,
        1298.690204792644,
        1298.9460933407431,
        1299.2499861988035,
        1299.660256393724,
        1299.958062541878,
        1300.2848427931158,
        1300.632907535479,
        1300.7720202542732,
        1301.2011660377411,
        1301.445459619326,
        1301.9740914052538,
        1302.2831604567054,
        1302.5139491842915,
        1302.8219213957411,
        1303.0238945582291,
        1303.4458787268582,
        1303.6843259448374,
        1304.0236053206563,
        1304.170663940476,
        1304.511160936563,
        1304.796235307192,
        1305.1260261154548,
        1305.3935672561515,
        1305.631068946578,
        1305.9747852547393,
        1306.3756463825907,
        1306.601195481228,
        1306.9044764546834,
        1307.210957000665,
        1307.483818311126,
        1307.7513265122209,
        1307.9890043946234,
        1308.2300047124963,
        1308.6697506688083,
        1308.9600032015087,
        1309.2819450359023,
        1309.531129808664,
        1309.7694343590638,
        1310.1389246675299
      ],
      "p50": [
        1296.1676538111763,
        1296.0194129693289,
        1295.8517212914085,
        1295.718768380701,
        1295.559131169416,
        1295.4089563696189,
        1295.2449662280956,
        1295.1160043406758,
        1294.9622842071344,
        1294.8241719901146,
        1294.6706240516692,
        1294.531617896214,
        1294.3924560234564,
        1294.2469973494524,
        1294.1031637826536,
        1293.9861211067678,
        1293.85139208986,
        1293.7040637493146,
        1293.608329496186,
        1293.4270967014209,
        1293.3079134424952,
        1293.1866652138378,
        1293.0844954353838,
        1292.9386796920717,
        1292.8196159380723,
        1292.7086310166248,
        1292.5155561863276,
        1292.4333256522398,
        1292.2373682303494,
        1292.028914973161,
        1291.9308206613,
        1291.829656631383,
        1291.7201054561656,
        1291.6024715455787,
        1291.4325767621692,
        1291.3308952670507,
        1291.2122324696047,
        1291.0912533777607,
        1290.9812067508992,
        1290.8005812406366,
        1290.6977829324255,
        1290.6134484396748,
        1290.5014132903125,
        1290.3968592641127,
        1290.292078134094,
        1290.1975127173246,
        1290.0494540690622,
        1289.9866262224684,
        1289.8710140135372,
        1289.7490942634959,
        1289.597520725837,
        1289.4720743931737,
        1289.3697155373497,
        1289.2595160878795,
        1289.1620553499615,
        1289.0784381292597,
        1289.0128523495034,
        1288.894007314222,
        1288.7992947766747,
        1288.7148550554277,
        1288.5996038322505,
        1288.4699624315572,
        1288.3652787159006,
        1288.3126703378048,
        1288.2297836580392,
        1288.149307044808,
        1288.0278793248162,
        1287.958797368001,
        1287.8646620982142,
        1287.8434888708546,
        1287.721217751101,
        1287.6619886190738,
        1287.57798840421,
        1287.4916118370845,
        1287.3218527455651,
        1287.2532168930381,
        1287.2078133094178,
        1287.0915032698088,
        1287.0060703037584,
        1286.936750063131,
        1286.932289201691,
        1286.8537346096177,
        1286.7856065892984,
        1286.6961495525825,
        1286.564414974772,
        1286.4615524254864,
        1286.3830621492232,
        1286.3215465200287,
        1286.1815040955576,
        1286.0791097267675,
        1285.9641652497712,
        1285.8949469246618,
        1285.7934315797766,
        1285.837875869864,
        1285.6829216358183,
        1285.5974788849744,
        1285.486306886261,
        1285.497031712347,
        1285.4249949621355,
        1285.3631859171373,
        1285.3203285807208,
        1285.2497012630865,
        1285.1317691470476,
        1285.0568902541627,
        1285.0030989641023,
        1285.0024844873942,
        1284.990215718941,
        1284.898815141977,
        1284.8077138771077,
        1284.7505282002812,
        1284.7914135262554,
        1284.755909232053,
        1284.65487474854,
        1284.6123157375491,
        1284.561418583994,
        1284.5564333517964,
        1284.4383708823086,
        1284.4160686818464,
        1284.3725463020821,
        1284.3325478077659,
        1284.2809637991745,
        1284.324552115122,
        1284.259222145392,
        1284.222825074672,
        1284.1212213462272,
        1284.0948306717637,
        1284.0262434844165,
        1283.939478800191,
        1283.8751748178888,
        1283.844993610499,
        1283.8598291643343,
        1283.7954333088292,
        1283.7146513740681,
        1283.55237780679,
        1283.5529049837448,
        1283.571278861696,
        1283.5584427665444,
        1283.577418863069,
        1283.4937310463135,
        1283.5203187564503,
        1283.4673958214394,
        1283.3921238320916,
        1283.4228957914324,
        1283.3896926355253,
        1283.3446482269392,
        1283.3613009906935,
        1283.46248818205,
        1283.3785855979002,
        1283.3963534227785,
        1283.4065171310813,
        1283.3263663836492,
        1283.3490104773514,
        1283.232907560229,
        1283.1564876167663,
        1283.1464891581234,
        1283.122232707032,
        1283.030643747458,
        1283.0584656779254,
        1283.0867867298457,
        1283.071593650869,
        1283.0023710521496,
        1283.067780105313,
        1282.989735310231,
        1283.0169939223076,
        1282.923426289324,
        1282.9476615534431,
        1282.9079333449583,
        1282.8471299064363,
        1282.8420009298834,
        1282.8188257272923,
        1282.8502242081045,
        1282.889149707719,
        1282.8947971396744,
        1282.954240556151,
        1282.918651498486,
        1283.0160512367208,
        1282.9381878139347,
        1282.9309014404319,
        1283.011334561278,
        1283.0454800018108,
        1282.9195659662664,
        1282.9675208663616,
        1282.9848259417395,
        1282.9146911547589,
        1282.8948889411695,
        1283.0028032473886,
        1283.0088568384422,
        1283.0498676093323,
        1282.996723083795,
        1283.0239525291317,
        1283.07411998329,
        1283.1424202630965,
        1283.1735120374049,
        1283.2147834788088,
        1283.2092521903378,
        1283.2660629502209,
        1283.2552340436366,
        1283.3323684397942,
        1283.3424096736849,
        1283.4100923862732,
        1283.4379065619291,
        1283.4806486415973,
        1283.4344160917838,
        1283.5080456245478,
        1283.4939893215414,
        1283.6161766308758,
        1283.647760441867,
        1283.7002224016776,
        1283.6373325003901,
        1283.7031627866488,
        1283.7027195780836,
        1283.766932476956,
        1283.8016333589098,
        1283.9269970234518,
        1283.8649449100626,
        1283.868227104675,
        1283.8781656366214,
        1283.9351094689073,
        1284.0651997883515,
        1284.1014891544805,
        1284.1460374942799,
        1284.1513011149348,
        1284.243379296622,
        1284.2774692796283,
        1284.388394933405,
        1284.4984468059251,
        1284.4983637904616,
        1284.5886403180286,
        1284.6148414224908,
        1284.63502148518,
        1284.5828344743322,
        1284.6679623249843,
        1284.7072525494243,
        1284.7479518346322,
        1284.824982082432,
        1284.7935194353547,
        1284.949747442609,
        1285.0486398721077,
        1285.0796373259655,
        1285.2579182595232,
        1285.2890133783176,
        1285.4557878811277,
        1285.5219993979426,
        1285.5829669196823,
        1285.723863304897,
        1285.7440536041338,
        1285.9411919517772,
        1286.0242339780993,
        1286.1479729199953,
        1286.184964250741,
        1286.1601005005423,
        1286.1749739361026,
        1286.322956815464,
        1286.365598018594,
        1286.5120915485745,
        1286.5686605371568,
        1286.7014652122907,
        1286.7535743893409,
        1286.8359743032972,
        1286.9204174712954,
        1286.9171542686727,
        1287.085892212369,
        1287.1527638665848,
        1287.2822563130258,
        1287.4042021458408,
        1287.4154159311079,
        1287.5204218237093,
        1287.5835009085347,
        1287.6477949754567,
        1287.80432967364,
        1287.9621973835717,
        1287.9972659741495,
        1288.1585298190862,
        1288.201189143871,
        1288.32840349656,
        1288.4601685609791,
        1288.5218222431638,
        1288.651169730364,
        1288.7401720909752,
        1288.8243826356088,
        1288.8583007526531,
        1288.923741076455,
        1289.0945890799317,
        1289.2325652600352,
        1289.240780872737,
        1289.508179038457,
        1289.57971990562,
        1289.6890978646873,
        1289.7983732247062,
        1289.974975375419,
        1290.0085872388252,
        1290.1552079726134,
        1290.2967716690116,
        1290.2752418484324,
        1290.4735476116812,
        1290.5985502526469,
        1290.6829055388348,
        1290.804541967239,
        1290.86832488663,
        1291.0031048258372,
        1291.203242118434,
        1291.3082163778201,
        1291.3812362895794,
        1291.4352151823173,
        1291.576056859295,
        1291.6921685690372,
        1292.0036798205292,
        1292.073506694092,
        1292.147519973294,
        1292.2715177804466,
        1292.4309712668792,
        1292.591912756454,
        1292.7499525003443,
        1292.9069795153735,
        1293.0743780350497,
        1293.0783477280993,
        1293.2810994529925,
        1293.5146620618216,
        1293.62413098423,
        1293.7952392865654,
        1293.9063852571321,
        1294.1337699512228,
        1294.2162539754927,
        1294.4367769330518,
        1294.5124649670242,
        1294.7388294702187,
        1294.9261342093828,
        1295.070199310644,
        1295.2160794024587,
        1295.3280407593445,
        1295.6478156710436,
        1295.83441441047,
        1296.0159962484408,
        1296.0644281831965,
        1296.1596366389022,
        1296.4586857365457,
        1296.6237712734358,
        1296.7080635536315,
        1296.9101539847109,
        1297.0571267339353,
        1297.3132509694406,
        1297.507985262937,
        1297.5857864466811,
        1297.6571218459562,
        1297.8002937304927,
        1297.9377152191046,
        1298.132649312173,
        1298.3320068823853,
        1298.5898005339895,
        1298.7588406494963,
        1298.990369299354,
        1299.092269214177,
        1299.2226808491182,
        1299.5175725849695,
        1299.610872550089,
        1299.8056566781565,
        1300.020246456162,
        1300.2182252020184,
        1300.423675351697,
        1300.668655583197,
        1300.772480522267,
        1300.95816618229,
        1301.1204983682292,
        1301.3681646909604,
        1301.4745508432295,
        1301.620434858222,
        1301.8072990754251,
        1301.9530996198941,
        1302.069465742096,
        1302.3518742653632,
        1302.5146878594746,
        1302.784725710835,
        1303.0761817988698,
        1303.2475810999974,
        1303.4406299745806,
        1303.7223302606335,
        1303.9478523164744,
        1304.2608518681534,
        1304.448645586757,
        1304.7020699274663,
        1304.8814532377992,
        1305.1167037029993,
        1305.3963897310136,
        1305.581136070737,
        1305.920472645557,
        1306.08931967244,
        1306.19931085983,
        1306.5071908084187,
        1306.7130739841914,
        1306.9463488086521,
        1307.1712803561359,
        1307.3529510235755,
        1307.5273744471212,
        1307.6080513869786,
        1307.8190919927847,
        1308.0338524665144,
        1308.2899599031261,
        1308.4226891782791,
        1308.7453878995566,
        1308.9275706156104,
        1309.2702346123897,
        1309.5134426006991,
        1309.8072722951695,
        1310.0758592832685,
        1310.3204278594749,
        1310.4940938780564,
        1310.8977554746853,
        1311.1036224206478,
        1311.3253836858962,
        1311.5689075092205,
        1311.8366300525167,
        1312.006608207366,
        1312.2287322445113,
        1312.4937064603735,
        1312.759177276424,
        1313.1101547667301,
        1313.3999846203458,
        1313.5472687915228,
        1313.847486292439,
        1314.0833693983186,
        1314.3098604921024,
        1314.5241311274722,
        1314.7944718893893,
        1315.0636092227023,
        1315.3499466006826,
        1315.6350052396958,
        1315.905260262116,
        1316.0933871486766,
        1316.3554299745451,
        1316.6283918052025,
        1316.9659538026817,
        1317.0870782080844,
        1317.2604295793412,
        1317.6407897042873,
        1317.8929809508336,
        1318.2085507460029,
        1318.453658039582,
        1318.6996739211716,
        1318.8607578739725,
        1319.0747184188174,
        1319.3448067928794,
        1319.6788502611407,
        1320.0768396746303,
        1320.2192948102927,
        1320.482565689339,
        1320.7068387985405,
        1321.0599960900836,
        1321.325157142398,
        1321.517062274764,
        1321.8796240875895,
        1322.0725555881884,
        1322.3332028253776,
        1322.6076858554015,
        1322.900523343835,
        1323.285465870643,
        1323.6184074229589,
        1323.8811261395192,
        1324.1042380784206,
        1324.4744191508416,
        1324.759580102092,
        1325.115121075361,
        1325.417858583754,
        1325.6833643175794,
        1325.9678325682173,
        1326.1780676045355,
        1326.6286113627384,
        1326.9670607163825,
        1327.3392227428367,
        1327.634540559422,
        1327.9294320855201,
        1328.2943732233944,
        1328.5682149942588,
        1328.921313957605,
        1329.082363276822,
        1329.489446665635,
        1329.804179956373,
        1330.0720468594295,
        1330.3407886103587,
        1330.7138662727923,
        1331.025318012139,
        1331.1909490686448,
        1331.6514166638322,
        1331.960650968676,
        1332.234948319703,
        1332.614505561061,
        1332.9575382807789,
        1333.2661345676945,
        1333.6417160524295,
        1333.9588245028797,
        1334.2685011055119,
        1334.6238256207248,
        1334.9147997600653,
        1335.2489436931721,
        1335.534738331005,
        1335.8354228483222,
        1336.250214953809,
        1336.5564958715202,
        1336.9202432281004,
        1337.2475691551183,
        1337.6296936089877,
        1337.9068586022727,
        1338.335598231983,
        1338.8111301932513,
        1339.1211591339143,
        1339.3962953668886
      ],
      "p75": [
        1296.1676538111763,
        1296.6714006375198,
        1296.9579194739292,
        1297.1399750040446,
        1297.304368491069,
        1297.4246744067395,
        1297.4787935766167,
        1297.5937147278783,
        1297.6553896167675,
        1297.7693715812886,
        1297.7951179947163,
        1297.8610106382894,
        1298.0163864089252,
        1298.0376953371551,
        1298.0451404254823,
        1298.0387824580926,
        1298.0256255171248,
        1298.0425420645802,
        1298.1138464952928,
        1298.1361606579176,
        1298.176980593474,
        1298.1658007940532,
        1298.1465168200316,
        1298.2472828774728,
        1298.2943000567159,
        1298.2810598581787,
        1298.2439327965967,
        1298.1789240053267,
        1298.1688858347702,
        1298.1630415784098,
        1298.1593163436814,
        1298.169907231084,
        1298.132939971836,
        1298.1350825940917,
        1298.130269074902,
        1298.1608789827235,
        1298.1792324008904,
        1298.17696797453,
        1298.172284590908,
        1298.2288712340974,
        1298.261830597337,
        1298.3126894957609,
        1298.2071510335034,
        1298.2576928840117,
        1298.2779861545325,
        1298.2428343777456,
        1298.2443053936702,
        1298.2717161653227,
        1298.2665467018064,
        1298.2505357747573,
        1298.1991289721072,
        1298.264432334946,
        1298.242698079742,
        1298.1946495724553,
        1298.1945923850271,
        1298.1258585275436,
        1298.0711703285785,
        1298.110247941904,
        1298.1567422368862,
        1298.1031574358108,
        1298.0201554859668,
        1298.0700870343471,
        1298.0698645713355,
        1298.0767742023343,
        1298.0059154052055,
        1298.069151311112,
        1298.0642659852865,
        1298.0473330474379,
        1298.0048805950682,
        1298.0475301486815,
        1298.0943863702082,
        1298.0055849308476,
        1297.9258054223344,
        1297.9199101077518,
        1297.9419036302572,
        1297.891261094605,
        1297.867928640406,
        1297.8468940461091,
        1297.8667455079858,
        1297.855529741196,
        1297.8789359480834,
        1297.9500054331465,
        1297.9560631597953,
        1297.8263251913827,
        1297.8342298986686,
        1297.8448524918813,
        1297.8486863026096,
        1297.8411693697917,
        1297.908137050184,
        1297.8733961981804,
        1297.8590920510956,
        1297.928213965858,
        1297.9084053237902,
        1297.9256878510737,
        1297.8871526110827,
        1297.9090490074807,
        1297.932498939043,
        1297.9339488674455,
        1297.8714467720501,
        1297.8068815162505,
        1297.8512658843265,
        1297.8752628022867,
        1297.8773780354015,
        1297.890224856016,
        1297.8884610915661,
        1297.9040637075243,
        1297.8835723356221,
        1297.9339835832968,
        1297.9595240777653,
        1298.0436482470918,
        1298.0415665975072,
        1297.9762806755364,
        1297.965087112472,
        1297.9173715120414,
        1297.956890230414,
        1297.97509731202,
        1297.9633412485118,
        1298.083771265482,
        1298.0787125546046,
        1298.1262141249154,
        1298.1204762659124,
        1298.1649499403675,
        1298.1486944502312,
        1298.1768750684066,
        1298.182284284187,
        1298.1832095614939,
        1298.2333164799543,
        1298.173569220126,
        1298.1910144152655,
        1298.1497239520545,
        1298.150705676653,
        1298.2000615118955,
        1298.267827533395,
        1298.3674118869092,
        1298.3915403912074,
        1298.3715035739547,
        1298.4134740032248,
        1298.511943746617,
        1298.5432287379708,
        1298.4948776173883,
        1298.426266651546,
        1298.591796479191,
        1298.5564311608623,
        1298.6242839243114,
        1298.6128830917673,
        1298.7212039917183,
        1298.7132287491222,
        1298.8753723352975,
        1298.8867154332427,
        1298.8962330636664,
        1298.9447282348956,
        1299.0176400271703,
        1299.1014713114635,
        1299.058147990907,
        1299.0276838687578,
        1299.0614004023814,
        1299.176077093635,
        1299.2106521374287,
        1299.2191049799458,
        1299.357194191263,
        1299.3756740340018,
        1299.3972200650674,
        1299.5170975573667,
        1299.6410252458245,
        1299.6945412944365,
        1299.7279044808,
        1299.7238019859678,
        1299.7401403121871,
        1299.8718373319375,
        1299.9179171543328,
        1299.9549200510905,
        1299.9820173667897,
        1300.049353302535,
        1300.199090119329,
        1300.1311394466438,
        1300.1051016899478,
        1300.2735996920164,
        1300.307164635502,
        1300.3655363535802,
        1300.433234096807,
        1300.4918857164807,
        1300.4973765209056,
        1300.6336340368061,
        1300.747205029546,
        1300.84569138619,
        1300.8530641698626,
        1300.9732551729294,
        1301.0559488246115,
        1301.1308473647305,
        1301.1051609307697,
        1301.2087160765593,
        1301.2322163224778,
        1301.239209127069,
        1301.3753152150448,
        1301.4351195245613,
        1301.5178902785126,
        1301.5640314319455,
        1301.685984868162,
        1301.7768331709337,
        1301.876005827047,
        1302.012794255678,
        1301.9785321343618,
        1301.9819162874192,
        1302.1191347147019,
        1302.2443944154443,
        1302.305980328032,
        1302.3327960702322,
        1302.472145791528,
        1302.5224364259816,
        1302.61975553247,
        1302.8042793258942,
        1302.7896679153127,
        1302.9172453471092,
        1302.9709495355442,
        1303.0798360874412,
        1303.247957515119,
        1303.394050332518,
        1303.4744453463022,
        1303.5290287080097,
        1303.637270855964,
        1303.6867265493815,
        1303.8426292188958,
        1303.933624947673,
        1304.0616390587807,
        1304.166528315416,
        1304.2631233909956,
        1304.3854126107567,
        1304.5059523024534,
        1304.6837263851357,
        1304.7247466775752,
        1304.7581395212503,
        1304.9226382831755,
        1305.1137941534507,
        1305.2233597019876,
        1305.2273158342368,
        1305.3520489811172,
        1305.432364924493,
        1305.5249652726905,
        1305.74080498671,
        1305.763208540942,
        1305.8380397774094,
        1305.9709530585687,
        1306.0844663688117,
        1306.1951410470365,
        1306.3063999344404,
        1306.4627633518937,
        1306.6268107537885,
        1306.6695313471896,
        1306.6871715941725,
        1306.838405011929,
        1306.9047128599034,
        1307.0437800359211,
        1307.1351660287066,
        1307.1478482924604,
        1307.200637910705,
        1307.3255552300234,
        1307.5049018366365,
        1307.6053646387463,
        1307.670991548405,
        1307.9163739688142,
        1308.100406126009,
        1308.2685409513326,
        1308.36151436189,
        1308.4359729968821,
        1308.4995020191805,
        1308.6912761276146,
        1308.758120828731,
        1308.9566447026214,
        1309.0240296936572,
        1309.3426041799853,
        1309.3349560944898,
        1309.4961203216121,
        1309.8307702182806,
        1309.9823114984836,
        1310.0356127950063,
        1310.0821679575456,
        1310.3267197396208,
        1310.44314145706,
        1310.6656711987848,
        1310.8034650215068,
        1310.9236037082715,
        1311.0541279581157,
        1311.1088624978397,
        1311.3827764201183,
        1311.4321131084823,
        1311.6396874430673,
        1311.7575370817958,
        1311.857231606338,
        1312.0186341440176,
        1312.2001237813508,
        1312.3480690326633,
        1312.5226385083467,
        1312.6108702698125,
        1312.8688688289012,
        1313.0590399120522,
        1313.2173730297343,
        1313.392341073461,
        1313.5106270262575,
        1313.8142240749673,
        1313.8817887770422,
        1314.2447411330381,
        1314.376830111046,
        1314.5020358373781,
        1314.6131352019825,
        1314.8851710928266,
        1315.0666880399156,
        1315.2918779447368,
        1315.518423757022,
        1315.626089270489,
        1315.7036092978485,
        1315.8503833148443,
        1316.082412901252,
        1316.204098649086,
        1316.477152248245,
        1316.6575095691346,
        1316.9158045556137,
        1316.98943284062,
        1317.1812202346382,
        1317.3227636073225,
        1317.5563473728773,
        1317.6674430565558,
        1317.8775243290925,
        1318.0083537993064,
        1318.201486293092,
        1318.4621305905453,
        1318.5602179447064,
        1318.7884250376976,
        1319.0038675271521,
        1319.2203894612833,
        1319.412841924628,
        1319.6870858187551,
        1319.7948227155161,
        1319.9214752743626,
        1320.2775192214303,
        1320.308823987115,
        1320.5493938151,
        1320.8250419730628,
        1320.9792320736842,
        1321.2222787297756,
        1321.5336172748164,
        1321.6548066383139,
        1321.9389424906517,
        1322.1275091128025,
        1322.2722449216749,
        1322.3907380367586,
        1322.585574635113,
        1322.7926291783301,
        1323.0483824222201,
        1323.2502752164726,
        1323.5239330942804,
        1323.6789802493784,
        1323.8278508725557,
        1324.126560613026,
        1324.389662206563,
        1324.6249487543846,
        1324.8640502764333,
        1325.0593031303654,
        1325.2971095106748,
        1325.52813296192,
        1325.7545555513987,
        1326.0795744921024,
        1326.2261927860277,
        1326.5739966995443,
        1326.8433369735649,
        1327.0946918463508,
        1327.3744142344715,
        1327.6468875200646,
        1327.7294222099986,
        1328.069590992675,
        1328.2259412717076,
        1328.3119697965258,
        1328.6008408011376,
        1328.8005904027789,
        1329.1238857178018,
        1329.4021794827975,
        1329.7060123209558,
        1330.0651999698205,
        1330.3050643578863,
        1330.4665643826186,
        1330.7081812602423,
        1330.8393941009126,
        1331.212089609461,
        1331.4392762070686,
        1331.6236107440845,
        1331.7187968431108,
        1332.0146396713237,
        1332.2357342910811,
        1332.5577913953693,
        1332.7742263918467,
        1332.9721794087673,
        1333.1347025708098,
        1333.3881450931626,
        1333.7633276390868,
        1334.0220472801034,
        1334.3568865212833,
        1334.451144951351,
        1334.8088110087974,
        1335.0326434575843,
        1335.2799927992287,
        1335.6261828315119,
        1335.835585787149,
        1336.1346280937116,
        1336.3765869428203,
        1336.6154403497187,
        1336.8861581126305,
        1337.2625832453855,
        1337.4851201010388,
        1337.6040318360458,
        1337.8877281981609,
        1338.1377235791333,
        1338.473625890165,
        1338.8306055033172,
        1339.130884918782,
        1339.4750322891489,
        1339.7230372987606,
        1340.0398194949694,
        1340.3662759795059,
        1340.6320090983484,
        1340.7769612421112,
        1341.045660043601,
        1341.3338348618329,
        1341.6713891032578,
        1342.1039178008905,
        1342.4576797249574,
        1342.7468646703933,
        1343.0445708976897,
        1343.2390105704503,
        1343.6452623677865,
        1343.8962260816782,
        1344.2254791156895,
        1344.4912105661833,
        1344.8118424074858,
        1344.9705291572482,
        1345.3114068558523,
        1345.625699195346,
        1345.9862026940464,
        1346.2775200233853,
        1346.6303232277705,
        1347.0473242466383,
        1347.40340473474,
        1347.7243141723804,
        1347.9798224178096,
        1348.4189254336693,
        1348.7260593611657,
        1349.133215230312,
        1349.4620086214688,
        1349.7600947654755,
        1350.0337227394389,
        1350.270791599513,
        1350.511304839441,
        1350.7731252249105,
        1350.987055180135,
        1351.4926082779587,
        1351.9121922904815,
        1352.1894969328482,
        1352.5369573537519,
        1352.7237231271688,
        1353.1044142870255,
        1353.358631580864,
        1353.715352179575,
        1354.0734915645353,
        1354.3605605077087,
        1354.569959864826,
        1354.9341470592515,
        1355.2927429623694,
        1355.6583313384717,
        1356.001164462632,
        1356.4925918307572,
        1356.9236318933333,
        1357.2903663026616,
        1357.6996944868997,
        1358.0712391323727,
        1358.4217502898314,
        1358.7773819370348,
        1359.2398823464318,
        1359.4603742099168,
        1359.789438082724,
        1360.2078217689186,
        1360.5466297190892,
        1361.0191534087487,
        1361.4198661512248,
        1361.7541449945406,
        1362.1282409131156,
        1362.4858128803935,
        1362.837666810801,
        1363.2506358764417,
        1363.5820382980517,
        1363.945086459307,
        1364.2691854025857,
        1364.6692088928944,
        1365.050395432986,
        1365.2566665746108,
        1365.5878286048965,
        1366.0570992766661,
        1366.4500923293956,
        1366.90905023655,
        1367.3884375407115,
        1367.6806181090947,
        1368.0468324784938,
        1368.3311738679588,
        1368.697404082413,
        1369.163585598103,
        1369.5439936548505,
        1369.9547152289576,
        1370.3420726009986
      ],
      "p95": [
        1296.1676538111763,
        1298.291011879046,
        1299.3062627236181,
        1300.1772238776075,
        1300.864868921515,
        1301.4305308618802,
        1301.980089743499,
        1302.5476800274746,
        1302.9789216666225,
        1303.423119677383,
        1303.7920394304203,
        1304.1856641891754,
        1304.641436799502,
        1305.0236489045913,
        1305.265732185889,
        1305.4659694206352,
        1305.772950664955,
        1306.0642748432479,
        1306.3890619422766,
        1306.674850942958,
        1306.8742290462712,
        1307.169438109756,
        1307.4867578787928,
        1307.819321050551,
        1308.1374793624827,
        1308.4101839678,
        1308.5110575793162,
        1308.814140948491,
        1308.9574832929263,
        1309.2254546524127,
        1309.4928407969446,
        1309.7072505462477,
        1309.8998603023258,
        1310.172846849528,
        1310.2370342054976,
        1310.445498232901,
        1310.668751856186,
        1310.932759259692,
        1311.1014929708751,
        1311.3565681608477,
        1311.527737847386,
        1311.7727747809547,
        1311.9351695659598,
        1312.005771627606,
        1312.1584092550534,
        1312.3352145828835,
        1312.519808300905,
        1312.5545844853082,
        1312.6418622900667,
        1312.9349419405416,
        1313.0030104378125,
        1313.2880635508982,
        1313.3927788318533,
        1313.4125278718277,
        1313.783862515062,
        1313.8653403323403,
        1313.9815172367462,
        1313.9691703809724,
        1314.058992570508,
        1314.098343338416,
        1314.2221099589701,
        1314.3496597540227,
        1314.5499304727987,
        1314.646119301188,
        1314.7592055328043,
        1314.913751674377,
        1315.018931502724,
        1315.2807326958937,
        1315.407160266103,
        1315.5892652576883,
        1315.7826801212939,
        1315.7866778261848,
        1315.887216214082,
        1315.9169120090162,
        1315.9569750582461,
        1316.2325104736265,
        1316.1951102524235,
        1316.3119798446428,
        1316.4759546980717,
        1316.7413248202827,
        1316.6308465690415,
        1316.9874858128712,
        1317.1699766201007,
        1317.1251805249224,
        1317.2333548746242,
        1317.336781450381,
        1317.504004111168,
        1317.5158973397188,
        1317.537216842015,
        1317.8387294603444,
        1317.9969777125254,
        1318.1346381052033,
        1318.1174404616866,
        1318.2229876685954,
        1318.263772910528,
        1318.5217352143961,
        1318.614778396955,
        1318.6230657424562,
        1318.6200198601107,
        1318.7163709446227,
        1318.8535286777485,
        1318.9488545334275,
        1318.912203374727,
        1319.0299710943152,
        1319.1500340297148,
        1319.255432895738,
        1319.519589305719,
        1319.7828072233867,
        1319.9530943457132,
        1320.1181359193204,
        1320.2023146558197,
        1320.5608021512944,
        1320.562093114667,
        1320.8341387785724,
        1321.0185250280174,
        1321.088973941208,
        1321.3512886173821,
        1321.38937993425,
        1321.4463668867124,
        1321.7418096794652,
        1321.7797239351687,
        1321.9461510025428,
        1322.2424664533862,
        1322.3637157726994,
        1322.4425952786273,
        1322.5298748590285,
        1322.4992875035412,
        1322.7799953347085,
        1322.7386619586389,
        1322.927399721059,
        1323.064915543868,
        1323.2187329511023,
        1323.3307532073325,
        1323.526489414406,
        1323.6509720279362,
        1323.7718690600107,
        1323.9263290235479,
        1323.9420854943423,
        1324.0657712094355,
        1324.0595089057554,
        1324.200908830891,
        1324.3215780759233,
        1324.4989636484058,
        1324.5583624103595,
        1324.5409980931568,
        1324.8306252736481,
        1325.035536928161,
        1325.244717763064,
        1325.4429601956285,
        1325.5571178909656,
        1325.5549804893087,
        1325.7334714703597,
        1325.8664787058287,
        1326.0273496606667,
        1326.194167057636,
        1326.2710712869625,
        1326.4300102564694,
        1326.8292037066306,
        1327.2070143278727,
        1327.1514040975082,
        1327.319411903076,
        1327.5081571972732,
        1327.5889166315312,
        1327.7661310600001,
        1327.7319715794756,
        1328.123367466528,
        1328.6823572925746,
        1328.4823610192948,
        1328.529021425505,
        1328.6035739435972,
        1328.9800303693112,
        1329.0817769356477,
        1329.3923992997009,
        1329.5674824885148,
        1329.5691145737753,
        1329.7434451769923,
        1329.9185159154888,
        1330.0955777810789,
        1330.2192171782583,
        1330.5808916802023,
        1330.6697308538426,
        1330.7368541747153,
        1330.9241236709865,
        1331.0685649711231,
        1331.1094415679993,
        1331.3271007957326,
        1331.514939477395,
        1331.3635146871097,
        1331.5439973122138,
        1331.5730102518492,
        1331.7853179816386,
        1331.8250822011614,
        1332.1588923625475,
        1332.1491019599243,
        1332.3273724315225,
        1332.5997355686616,
        1332.7455440186511,
        1332.930777150034,
        1332.9311559440653,
        1333.0973369954115,
        1333.1705890035093,
        1333.3697827283927,
        1333.474920381184,
        1333.605568681644,
        1333.9341037562995,
        1334.0512784321754,
        1334.0111250452426,
        1334.1831120596985,
        1334.3789278008726,
        1334.4699588671465,
        1334.8548182753195,
        1334.945350808875,
        1335.336637039225,
        1335.3499532734184,
        1335.4862333052545,
        1335.5729422148884,
        1335.6681730667117,
        1335.7361678493587,
        1336.026741066284,
        1336.3007574532587,
        1336.3819370067886,
        1336.7572729859348,
        1336.9543544778355,
        1337.1557200894229,
        1337.3031279804695,
        1337.3705093703293,
        1337.5418870118954,
        1337.8974317781008,
        1338.2831807739647,
        1338.3842293506152,
        1338.438525436131,
        1338.6243242173066,
        1338.9113711074888,
        1339.2686225305933,
        1339.165355352949,
        1339.591789451024,
        1339.8657075161086,
        1340.0781794392567,
        1340.2056710734453,
        1340.263431989312,
        1340.4742908222997,
        1340.8968307785478,
        1341.2137108861157,
        1341.1198600161672,
        1341.338715322925,
        1341.4335754416018,
        1341.4691531927976,
        1341.7498512898278,
        1341.9225151510145,
        1341.9801467724105,
        1342.3060330654014,
        1342.5025072854694,
        1342.5183213637183,
        1342.5598524693605,
        1342.7085304097552,
        1343.13512444473,
        1343.23790163746,
        1343.4747015050893,
        1343.900234437183,
        1344.1388052629497,
        1344.3556988881014,
        1344.6007578656672,
        1344.8784557867803,
        1344.9655144999256,
        1345.1049363744992,
        1345.2083536976943,
        1345.2645100410705,
        1345.6594586995477,
        1345.6385273165122,
        1346.0053597653807,
        1346.2785500105845,
        1346.5911527361275,
        1346.8300213217108,
        1346.869181656309,
        1346.9234899455919,
        1347.2148362578262,
        1347.3363450496124,
        1347.4284422841654,
        1347.6950844102164,
        1347.8532879542358,
        1348.0646932158938,
        1348.1230371887304,
        1348.428816998518,
        1348.4661441408282,
        1348.565116735398,
        1348.8693380644704,
        1349.1585752666317,
        1349.226726451388,
        1349.5193881155512,
        1349.902096368433,
        1350.1164198919976,
        1350.377689013021,
        1350.8586390587593,
        1351.422574269435,
        1351.5419667257931,
        1351.8846124527497,
        1351.903004585506,
        1352.2152331142886,
        1352.6542295460479,
        1353.0084088506708,
        1352.9953191135467,
        1353.4286508669252,
        1353.6720571866606,
        1353.579068691153,
        1353.8060173970716,
        1354.1250296285043,
        1354.3460393511216,
        1354.620930642612,
        1354.910231122084,
        1354.9974881266216,
        1355.3483472664518,
        1355.7586732988773,
        1355.9747753850781,
        1356.2540461149945,
        1356.4726564251655,
        1356.6203263887019,
        1356.755098929975,
        1356.977882111225,
        1357.2429884583378,
        1357.7226624512468,
        1357.9200110290994,
        1358.0668466379525,
        1358.5182466679967,
        1358.5186383057812,
        1358.7642206307207,
        1359.0471215953999,
        1359.0104936252699,
        1359.4104981739824,
        1359.7425120230137,
        1359.8795421173998,
        1360.2893426156181,
        1360.563064576256,
        1360.6116646087692,
        1360.6796756614447,
        1360.9827927645126,
        1361.0998253867058,
        1361.636951155019,
        1361.8473894207775,
        1362.060343329171,
        1362.562659292803,
        1362.9053652017374,
        1363.1082357950263,
        1363.4441039598876,
        1363.4948915930217,
        1363.744153846928,
        1363.897913271274,
        1364.186724389391,
        1364.5630212325877,
        1365.0747706609786,
        1365.1858231637443,
        1365.6850957931867,
        1365.8985705965833,
        1366.2664369118208,
        1366.5520227113157,
        1366.6438331218667,
        1366.9321405113994,
        1367.2546170500937,
        1367.406945001392,
        1367.6003660990025,
        1368.0768238879573,
        1368.2277849064424,
        1368.42905954574,
        1368.9383813226991,
        1369.3551462901712,
        1369.5752916683216,
        1369.8836345443383,
        1370.3122848608816,
        1370.3224230005455,
        1370.465454610477,
        1370.7471358560026,
        1371.1488650454764,
        1371.392127177766,
        1371.8776319769556,
        1372.045463887682,
        1372.6373930832485,
        1372.840821669963,
        1373.2774256842997,
        1373.8025436484693,
        1373.957832685549,
        1373.9895982588807,
        1374.1758988921727,
        1374.584633936216,
        1374.7974089964353,
        1375.388456967785,
        1375.7121325461437,
        1376.0340715744421,
        1376.4501945653683,
        1376.9941035986903,
        1377.194971253871,
        1377.1066083998394,
        1377.9651909731833,
        1378.2121126120428,
        1378.6390390354286,
        1378.7729190022667,
        1378.9861382947174,
        1379.2669794738447,
        1379.6084547829669,
        1380.034357899642,
        1380.2945673981696,
        1380.7456951528777,
        1381.25756199484,
        1381.458548290364,
        1381.6987670305873,
        1382.028385730861,
        1382.3872877142908,
        1382.732616462921,
        1383.0628442119144,
        1383.486672379796,
        1383.8651525935777,
        1384.3064970051553,
        1384.8090980071736,
        1384.9868811434153,
        1385.4249774066457,
        1385.7010461288394,
        1386.0305757384535,
        1386.5292722934203,
        1387.0216634059122,
        1387.0242431873774,
        1387.6010502236493,
        1387.9286113194607,
        1388.0392088653437,
        1388.3980983025422,
        1388.820961457806,
        1389.1036117874978,
        1389.4166727424256,
        1389.7284181479606,
        1390.1919980157106,
        1390.739151067018,
        1391.0756836349133,
        1391.5070932567498,
        1391.770672396048,
        1392.1591377710909,
        1392.5803129055957,
        1393.1302172928183,
        1393.4588978579652,
        1393.9069229020322,
        1394.2420015102252,
        1394.7374118398218,
        1395.0576182225961,
        1395.6340200850875,
        1395.9426353593744,
        1396.3841070421167,
        1396.756350718903,
        1397.207302895792,
        1397.7234715226136,
        1398.1109104482964,
        1398.5254421196437,
        1398.9154736019816,
        1399.066397453517,
        1399.6795939965075,
        1399.6184616475534,
        1399.8254943161135,
        1400.399858622437,
        1400.7053565240083,
        1401.0082267479975,
        1401.4597976883886,
        1402.033793028345,
        1402.5423860419237,
        1403.0662507837806,
        1403.424842637366,
        1403.934306595849,
        1404.480230292097,
        1404.563126872643,
        1404.743637888657,
        1405.279558549741,
        1405.285051722175,
        1405.629552143297,
        1406.2123114936087,
        1406.5978692386984,
        1407.2152290837623,
        1407.7406617946685,
        1408.1135910382043,
        1408.1261482646057,
        1408.665988641574,
        1409.2993775479417,
        1409.5187241611509,
        1409.8561993720339,
        1410.3843637142108,
        1410.9792068249665,
        1411.1906518839367,
        1411.5883026988517,
        1411.8538929946944,
        1412.168528959599,
        1412.5258835699774,
        1412.937171206202,
        1413.0689553628265,
        1413.7176098998148,
        1414.2853259101475,
        1415.0588881049866,
        1415.3237803671302,
        1415.8505467260059,
        1416.3597995851696,
        1416.9434484298329,
        1417.313093242864,
        1417.7096252381778,
        1418.191843358425,
        1418.5733262709819,
        1418.8892859537395,
        1419.4009053390853,
        1419.6398840853744,
        1420.0870091252289,
        1420.6064995270658,
        1421.0424907450565,
        1421.5278668279843,
        1422.204227009205
      ]
    },
    "final_histogram": {
      "bins": [
        873.74,
        410471288.61,
        820941703.49,
        1231412118.36,
        1641882533.23,
        2052352948.1,
        2462823362.97,
        2873293777.85,
        3283764192.72,
        3694234607.59,
        4104705022.46,
        4515175437.33,
        4925645852.21,
        5336116267.08,
        5746586681.95,
        6157057096.82,
        6567527511.7,
        6977997926.57,
        7388468341.44,
        7798938756.31,
        8209409171.18,
        8619879586.06,
        9030350000.93,
        9440820415.8,
        9851290830.67,
        10261761245.54,
        10672231660.42,
        11082702075.29,
        11493172490.16,
        11903642905.03,
        12314113319.91,
        12724583734.78,
        13135054149.65,
        13545524564.52,
        13955994979.39,
        14366465394.27,
        14776935809.14,
        15187406224.01,
        15597876638.88,
        16008347053.75,
        16418817468.63,
        16829287883.5,
        17239758298.37,
        17650228713.24,
        18060699128.11,
        18471169542.99,
        18881639957.86,
        19292110372.73,
        19702580787.6,
        20113051202.48,
        20523521617.35,
        20933992032.22,
        21344462447.09,
        21754932861.96,
        22165403276.84,
        22575873691.71,
        22986344106.58,
        23396814521.45,
        23807284936.32,
        24217755351.2,
        24628225766.07,
        25038696180.94,
        25449166595.81,
        25859637010.69,
        26270107425.56,
        26680577840.43,
        27091048255.3,
        27501518670.17,
        27911989085.05,
        28322459499.92,
        28732929914.79,
        29143400329.66,
        29553870744.53,
        29964341159.41,
        30374811574.28,
        30785281989.15,
        31195752404.02,
        31606222818.9,
        32016693233.77,
        32427163648.64
      ],
      "counts": [
        24999,
        0,
        0,
        0,
        0,
        0,
        0,
        0,
        0,
        0,
        0,
        0,
        0,
        0,
        0,
        0,
        0,
        0,
        0,
        0,
        0,
        0,
        0,
        0,
        0,
        0,
        0,
        0,
        0,
        0,
        0,
        0,
        0,
        0,
        0,
        0,
        0,
        0,
        0,
        0,
        0,
        0,
        0,
        0,
        0,
        0,
        0,
        0,
        0,
        0,
        0,
        0,
        0,
        0,
        0,
        0,
        0,
        0,
        0,
        0,
        0,
        0,
        0,
        0,
        0,
        0,
        0,
        0,
        0,
        0,
        0,
        0,
        0,
        0,
        0,
        0,
        0,
        0,
        0,
        1
      ]
    },
    "drawdown_histogram": {
      "bins": [
        0.7,
        1.33,
        1.95,
        2.58,
        3.21,
        3.84,
        4.47,
        5.09,
        5.72,
        6.35,
        6.98,
        7.61,
        8.23,
        8.86,
        9.49,
        10.12,
        10.74,
        11.37,
        12.0,
        12.63,
        13.26,
        13.88,
        14.51,
        15.14,
        15.77,
        16.4,
        17.02,
        17.65,
        18.28,
        18.91,
        19.53,
        20.16,
        20.79,
        21.42,
        22.05,
        22.67,
        23.3,
        23.93,
        24.56,
        25.19,
        25.81,
        26.44,
        27.07,
        27.7,
        28.32,
        28.95,
        29.58,
        30.21,
        30.84,
        31.46,
        32.09,
        32.72,
        33.35,
        33.98,
        34.6,
        35.23,
        35.86,
        36.49,
        37.12,
        37.74,
        38.37,
        39.0,
        39.63,
        40.25,
        40.88,
        41.51,
        42.14,
        42.77,
        43.39,
        44.02,
        44.65,
        45.28,
        45.91,
        46.53,
        47.16,
        47.79,
        48.42,
        49.04,
        49.67,
        50.3
      ],
      "counts": [
        822,
        3696,
        4822,
        4366,
        3547,
        2578,
        1722,
        1195,
        813,
        481,
        295,
        209,
        111,
        67,
        62,
        52,
        35,
        17,
        22,
        14,
        8,
        8,
        7,
        7,
        4,
        5,
        1,
        4,
        4,
        3,
        6,
        3,
        0,
        2,
        2,
        3,
        0,
        0,
        0,
        1,
        0,
        0,
        0,
        0,
        0,
        1,
        0,
        2,
        0,
        0,
        0,
        0,
        0,
        0,
        0,
        0,
        1,
        0,
        0,
        1,
        0,
        0,
        0,
        0,
        0,
        0,
        0,
        0,
        0,
        0,
        0,
        0,
        0,
        0,
        0,
        0,
        0,
        0,
        0,
        1
      ]
    }
  },
  "risk_metrics": {
    "var_95": {
      "confidence": 0.95,
      "loss_pct": 2.28,
      "loss_usd": 29.5,
      "threshold_value_usd": 1266.67
    },
    "var_99": {
      "confidence": 0.99,
      "loss_pct": 5.45,
      "loss_usd": 70.69,
      "threshold_value_usd": 1225.48
    },
    "cvar_95": {
      "confidence": 0.95,
      "expected_loss_pct": 4.46,
      "expected_loss_usd": 57.79
    },
    "probabilities": {
      "prob_loss": 15.8,
      "prob_gain_20": 0.4,
      "prob_loss_30": 0.0
    },
    "multi_horizon": {
      "21": {
        "percentiles": {
          "1%": 1267.1,
          "5%": 1279.07,
          "10%": 1282.86,
          "25%": 1288.07,
          "50%": 1293.19,
          "75%": 1298.17,
          "90%": 1303.45,
          "95%": 1307.17,
          "99%": 1320.39
        },
        "returns_pct": {
          "1%": -2.2,
          "5%": -1.3,
          "10%": -1.0,
          "25%": -0.6,
          "50%": -0.2,
          "75%": 0.2,
          "90%": 0.6,
          "95%": 0.8,
          "99%": 1.9
        },
        "mean": 1293.32,
        "median": 1293.19
      },
      "63": {
        "percentiles": {
          "1%": 1243.75,
          "5%": 1262.85,
          "10%": 1269.34,
          "25%": 1278.62,
          "50%": 1288.31,
          "75%": 1298.08,
          "90%": 1307.74,
          "95%": 1314.65,
          "99%": 1335.77
        },
        "returns_pct": {
          "1%": -4.0,
          "5%": -2.6,
          "10%": -2.1,
          "25%": -1.4,
          "50%": -0.6,
          "75%": 0.1,
          "90%": 0.9,
          "95%": 1.4,
          "99%": 3.1
        },
        "mean": 1288.68,
        "median": 1288.31
      },
      "126": {
        "percentiles": {
          "1%": 1221.06,
          "5%": 1247.01,
          "10%": 1256.54,
          "25%": 1269.95,
          "50%": 1284.03,
          "75%": 1298.23,
          "90%": 1312.42,
          "95%": 1322.5,
          "99%": 1351.86
        },
        "returns_pct": {
          "1%": -5.8,
          "5%": -3.8,
          "10%": -3.1,
          "25%": -2.0,
          "50%": -0.9,
          "75%": 0.2,
          "90%": 1.3,
          "95%": 2.0,
          "99%": 4.3
        },
        "mean": 1284.68,
        "median": 1284.03
      },
      "252": {
        "percentiles": {
          "1%": 1202.22,
          "5%": 1233.95,
          "10%": 1246.93,
          "25%": 1265.87,
          "50%": 1286.32,
          "75%": 1307.14,
          "90%": 1327.74,
          "95%": 1342.52,
          "99%": 1387.04
        },
        "returns_pct": {
          "1%": -7.2,
          "5%": -4.8,
          "10%": -3.8,
          "25%": -2.3,
          "50%": -0.8,
          "75%": 0.8,
          "90%": 2.4,
          "95%": 3.6,
          "99%": 7.0
        },
        "mean": 2130954.62,
        "median": 1286.32
      },
      "504": {
        "percentiles": {
          "1%": 1225.48,
          "5%": 1266.67,
          "10%": 1283.61,
          "25%": 1310.14,
          "50%": 1339.4,
          "75%": 1370.34,
          "90%": 1400.51,
          "95%": 1422.2,
          "99%": 1482.74
        },
        "returns_pct": {
          "1%": -5.5,
          "5%": -2.3,
          "10%": -1.0,
          "25%": 1.1,
          "50%": 3.3,
          "75%": 5.7,
          "90%": 8.1,
          "95%": 9.7,
          "99%": 14.4
        },
        "mean": 1326433.7,
        "median": 1339.4
      }
    },
    "median_end_usd": 1339.4,
    "mean_end_usd": 1326433.7
  },
  "stress_tests": [
    {
      "name": "Crash rynkowy",
      "description": "Wszystkie aktywa tracą 30% wartości jednocześnie",
      "shocked_value_usd": 907.32,
      "immediate_pnl_pct": -30.0,
      "median_end_usd": 937.47,
      "var_95_pct": 2.0
    },
    {
      "name": "Szok sektorowy fotoniki",
      "description": "Spółki fotoniki/półprzewodnikowe -40%, IVV bez zmian",
      "shocked_value_usd": 796.47,
      "immediate_pnl_pct": -38.6,
      "median_end_usd": 818.43,
      "var_95_pct": 2.4
    },
    {
      "name": "Szok walutowy (GBP/EUR -15%)",
      "description": "Deprecjacja GBP i EUR o 15% wobec USD",
      "shocked_value_usd": 1186.59,
      "immediate_pnl_pct": -8.5,
      "median_end_usd": 1224.68,
      "var_95_pct": 2.3
    },
    {
      "name": "Stagflacja",
      "description": "Oczekiwane zwroty o 50% niższe, zmienność +30%",
      "shocked_value_usd": 1296.17,
      "immediate_pnl_pct": 0.0,
      "median_end_usd": 1080.02,
      "var_95_pct": 22.1
    }
  ],
  "correlations": {
    "tickers": [
      "M7U.DE",
      "AAOI",
      "AXTI",
      "SOI.PA",
      "IQE.L",
      "LITE",
      "LNSR",
      "IVV",
      "P4O.DE"
    ],
    "matrix": [
      [
        1.0,
        0.069,
        0.113,
        0.143,
        0.119,
        0.088,
        -0.025,
        0.173,
        0.075
      ],
      [
        0.069,
        1.0,
        0.24,
        0.135,
        0.095,
        0.423,
        0.045,
        0.326,
        -0.011
      ],
      [
        0.113,
        0.24,
        1.0,
        0.189,
        0.144,
        0.357,
        0.077,
        0.354,
        0.03
      ],
      [
        0.143,
        0.135,
        0.189,
        1.0,
        0.236,
        0.185,
        0.033,
        0.279,
        0.08
      ],
      [
        0.119,
        0.095,
        0.144,
        0.236,
        1.0,
        0.162,
        0.007,
        0.226,
        0.083
      ],
      [
        0.088,
        0.423,
        0.357,
        0.185,
        0.162,
        1.0,
        0.026,
        0.486,
        0.018
      ],
      [
        -0.025,
        0.045,
        0.077,
        0.033,
        0.007,
        0.026,
        1.0,
        0.046,
        -0.014
      ],
      [
        0.173,
        0.326,
        0.354,
        0.279,
        0.226,
        0.486,
        0.046,
        1.0,
        0.074
      ],
      [
        0.075,
        -0.011,
        0.03,
        0.08,
        0.083,
        0.018,
        -0.014,
        0.074,
        1.0
      ]
    ]
  }
}